EC_Controller.py
EC_Controller-1.0.dist-info/LICENSE
EC_Controller-1.0.dist-info/METADATA
EC_Controller-1.0.dist-info/WHEEL
EC_Controller-1.0.dist-info/top_level.txt
EC_Controller-1.0.dist-info/RECORD
